idmtheory/__init__.py
idmtheory/characters.py
idmtheory/chords.py
idmtheory/notes.py
idmtheory/scales.py
idmtheory/tone_intervals.py
idmtheory-0.4.0.dist-info/licenses/LICENCE
idmtheory-0.4.0.dist-info/METADATA
idmtheory-0.4.0.dist-info/WHEEL
idmtheory-0.4.0.dist-info/top_level.txt
idmtheory-0.4.0.dist-info/RECORD
