Metadata-Version: 2.4
Name: idmtheory
Version: 0.4.0
Summary: A module for music theory concepts including tone intervals, notes, scales and chords.
Author-email: Improper Decoherence <improper.decoherence@proton.me>
License-Expression: MIT
Project-URL: Homepage, https://codeberg.org/decoherence/idmtheory
Classifier: Programming Language :: Python :: 3
Classifier: Operating System :: OS Independent
Requires-Python: >=3.12
License-File: LICENCE
Requires-Dist: idroman>=0.1.0
Provides-Extra: test
Requires-Dist: pytest>=8.4; extra == "test"
Dynamic: license-file
